conanbuild/README.md
conanbuild/__init__.py
conanbuild/builder.py
conanbuild/conanfile.py
conanbuild/targets/CameraCtrl.py.in
conanbuild/targets/MaxDS.py.in
conanbuild/targets/MaxME.py.in
conanbuild/targets/OpenCV.py.in
conanbuild/targets/OpenSSL.py.in
conanbuild/targets/Sentry.py.in
conanbuild/targets/StackEngine.py.in
conanbuild/targets/abseil.py.in
conanbuild/targets/cairo.py.in
conanbuild/targets/disruptor.py.in
conanbuild/targets/expat.py.in
conanbuild/targets/fdk-aac.py.in
conanbuild/targets/freetype.py.in
conanbuild/targets/gflags.py.in
conanbuild/targets/googletest.py.in
conanbuild/targets/gpu_sdk.py.in
conanbuild/targets/h323plus.py.in
conanbuild/targets/harfbuzz.py.in
conanbuild/targets/intel_media_sdk.py.in
conanbuild/targets/jsoncpp.py.in
conanbuild/targets/libcares.py.in
conanbuild/targets/libcpuinfo.py.in
conanbuild/targets/libcurl.py.in
conanbuild/targets/libdb.py.in
conanbuild/targets/libevent.py.in
conanbuild/targets/libfacesdk.py.in
conanbuild/targets/libfdk_aac.py.in
conanbuild/targets/libjpeg.py.in
conanbuild/targets/libmysqlconnectorc.py.in
conanbuild/targets/libne10.py.in
conanbuild/targets/libpcap.py.in
conanbuild/targets/libpng.py.in
conanbuild/targets/libqrencode.py.in
conanbuild/targets/libressl.py.in
conanbuild/targets/libsndfile.py.in
conanbuild/targets/libsrtp.py.in
conanbuild/targets/libtiff.py.in
conanbuild/targets/libvpx.py.in
conanbuild/targets/libx264.py.in
conanbuild/targets/libx264_record.py.in
conanbuild/targets/libxaac.py.in
conanbuild/targets/libyuv.py.in
conanbuild/targets/live555.py.in
conanbuild/targets/lua.py.in
conanbuild/targets/mlDNS.py.in
conanbuild/targets/mlWidgets.py.in
conanbuild/targets/mlbase.py.in
conanbuild/targets/mlkupdator.py.in
conanbuild/targets/mlts.py.in
conanbuild/targets/nlohmann.py.in
conanbuild/targets/ogg.py.in
conanbuild/targets/openh264.py.in
conanbuild/targets/opus.py.in
conanbuild/targets/pcre.py.in
conanbuild/targets/pjsip.py.in
conanbuild/targets/plfutils.py.in
conanbuild/targets/ptlib.py.in
cpptools-1.2.10.dist-info/LICENSE.txt
cpptools-1.2.10.dist-info/METADATA
cpptools-1.2.10.dist-info/WHEEL
cpptools-1.2.10.dist-info/entry_points.txt
cpptools-1.2.10.dist-info/top_level.txt
cpptools-1.2.10.dist-info/RECORD
