Metadata-Version: 2.1
Name: cpptools
Version: 1.2.10
Summary: The toolset for c/c++ project & package.
Home-page: https://gitlab.gz.cvte.cn/1602/cpptools
Author: TigerLau
Author-email: tigerliu1985@hotmail.com
Classifier: Programming Language :: Python :: 3
Classifier: License :: OSI Approved :: MIT License
Classifier: Operating System :: OS Independent
Requires-Python: >=3
License-File: LICENSE.txt
